{
  "template_id": "tpl_pro_002",
  "template_name": "Finance Executive",
  "category": "Professional",
  "description": "An authoritative single-column layout with centered titles, dense formatting, and deep navy accents, designed for finance executives.",
  "layout_metadata": {
    "column_count": 1,
    "sidebar_position": "none",
    "structural_alignment": "justified",
    "information_density": "dense",
    "visual_emphasis": "borders",
    "typography": {
      "heading": "FontStack-P2A",
      "body": "FontStack-P2B",
      "accent": "FontStack-P2C"
    },
    "spacing": {
      "margin": "15px",
      "line_height": 1.2,
      "section_gap": "15px"
    },
    "color_palette": {
      "primary": "#1e3a8a",
      "secondary": "#b45309",
      "text": "#111111",
      "background": "#ffffff"
    },
    "has_photo": false,
    "responsive_behavior": "stack-on-mobile"
  },
  "sections": {
    "order": [
      "summary",
      "experience",
      "education",
      "skills"
    ],
    "visibility": {
      "summary": true,
      "skills": true,
      "experience": true,
      "education": true,
      "projects": true
    }
  },
  "ats_score": 97,
  "suitable_professions": [
    "Finance",
    "Banking",
    "Corporate Accounting"
  ]
}